{
  "timestamp": "2025-12-01T17:00:58.850063706+08:00",
  "cycle_number": 1485,
  "system_prompt": "",
  "input_prompt": "",
  "cot_trace": "**思维链分析：**\n\n**交易频率检查（首先，硬约束）：**\n- 最近1小时已交易次数：0次\n- 交易频率状态：\u003c2次，可以继续寻找A级机会\n- 交易频率限制：最近1小时最多2次交易\n\n**市场环境判断：**\n- **BTC 4小时趋势**：EMA20(90394) \u003e EMA50(89914)，MACD(666.7)为正但持续下降，RSI14(55.28)中性。整体为**上升趋势中的回调**，但动量减弱。\n- **环境影响**：整体处于上升趋势中的回调阶段，做多需等待明确的回调结束信号，做空需谨慎（逆大趋势）。\n\n**长线趋势（4小时）：**\n- **BTC**：EMA20 \u003e EMA50，MACD为正但下降，RSI14中性。趋势为**上升趋势中的回调**。\n- **ETH**：EMA20(2999) \u003e EMA50(2979)，MACD(21.3)为正但下降，RSI14(51.7)中性。趋势为**上升趋势中的回调**。\n- **其他币种**：多数处于震荡或弱势回调中，无明显强势趋势。\n\n**中期趋势（1小时）：**\n- **BTC**：EMA20(90792) \u003e EMA50(90663)，但MACD(-73.3)为负且下降，RSI14(47.8)中性偏弱。**1小时级别已转为下跌**，与4小时趋势冲突。\n- **ETH**：EMA20(3009) \u003c EMA50(3012)，MACD(-9.3)为负，RSI14(43.0)中性偏弱。**1小时级别转为下跌**。\n- **关键发现**：**1小时趋势与4小时趋势出现背离**。4小时上升，但1小时下跌，这可能导致大额回撤。需要等待多周期重新一致。\n\n**短线趋势（3分钟）：**\n- **BTC**：价格(90720)略低于EMA20(90861)，MACD(-33.6)为负且持续下降，RSI7(31.4)接近超卖。**短期处于下跌中，但RSI7已接近超卖区**。\n- **ETH**：价格(2997)略低于EMA20(2999)，MACD(-1.1)为负，RSI7(40.8)中性。短期弱势。\n- **极度超卖反弹检测（BTC）**：\n  - RSI7最低触及19.95（极度超卖），当前反弹至31.4。\n  - 3分钟MACD仍为负(-33.6)，未金叉。\n  - 成交量：当前3分钟成交量(872.9)远低于平均(5300.7)，反弹未放量。\n  - K线：最新价格(90720)高于前一根(90667)，但未形成连续阳线。\n  - 4小时动量：MACD正值持续收窄（从1079降至666），动量减弱。\n  - **结论**：出现了**极度超卖（RSI7\u003c20）**，但**反弹信号不明确**（MACD未金叉、成交量未放大、未连续阳线）。不符合“极度超卖反弹模式”的完整条件，需要等待更明确的反弹确认。\n\n**多周期确认：**\n- **BTC**：4小时（上升）、1小时（下跌）、3分钟（下跌）。**三个周期趋势不一致**，1小时与3分钟下跌，4小时上升。这是典型的**趋势冲突**状态，应观望。\n- **ETH**：情况类似，多周期不一致。\n- **关键原则**：三个周期不一致时，必须观望，不交易。\n\n**转折点识别：**\n- **潜在做多机会（BTC）**：价格已从低点90667反弹，RSI7从19.95反弹至31.4，显示超卖后有一定买盘。但**缺乏关键确认信号**（MACD金叉、成交量放大）。\n- **潜在做空机会**：1小时和3分钟趋势向下，但逆4小时大趋势，风险较高。\n\n**盈亏比与盈利空间评估（假设交易）：**\n- 当前市场多周期冲突，趋势不明。任何交易的预期盈利和风险都难以清晰界定，盈亏比计算不可靠。\n- **预期盈利 × 杠杆倍数**：在趋势不明时，预期盈利空间小，难以满足 **\u003e20%** 的标准。\n\n**持仓评估（关键 - 减少短持仓，避免快进快出）：**\n- **当前持仓**：BTCUSDT LONG，入场价86213，当前价86836，盈利+0.72%（价格），+14.35%（保证金）。\n- **持仓时间**：2小时43分钟，远大于15分钟最小要求，避免了快进快出。\n- **⚠️ 最高优先级：判断是否是真正的趋势变化（使用综合评分系统）：**\n  - **多周期确认（40分）**：\n    - 4小时级别（15分）：价格(90720) \u003e EMA20(90394)，MACD为正，**趋势未反转**。得分：0分。\n    - **1小时级别（20分，关键）**：价格(90720) \u003c EMA20(90792)，MACD为负且下降，**1小时趋势已转为下跌**。得分：价格跌破EMA20(+8)，MACD死叉且为负(+8)，共+16分。\n    - 3分钟级别（5分）：价格略低于EMA20，MACD为负。得分：+2分。\n    - 多周期一致性：4小时上升，1小时下跌，不一致。得分：+1分（只有1个周期确认反转）。\n    - **小计：19分**。\n  - **成交量确认（25分）**：1小时成交量(872.9)远低于平均(5300.7)，下跌未放量。得分：0分。\n  - **价格突破关键位（20分）**：价格未跌破最近显著低点（需查看更早数据，但当前价格高于入场价）。得分：0分。\n  - **技术指标确认（10分）**：无顶背离，RSI未超买。得分：0分。\n  - **持续时间确认（5分）**：1小时下跌趋势刚开始。得分：0分。\n  - **总分计算**：19 + 0 + 0 + 0 + 0 = **19分**。\n  - **综合评分判断**：**评分19分 \u003c 40分**，属于**短暂波动**，而非真正的趋势变化。\n  - **考虑杠杆影响**：当前杠杆20x（高杠杆），评分阈值降低5分（≥55分止盈）。19分远低于55分。\n- **移动止损检查（关键 - 每次必须检查）：**\n  - 当前盈利（价格）：(86836 - 86213) / 86213 = 0.72%。\n  - 初始止损距离（假设2%）：未提供初始止损价，但强平价82277距离入场价约4.6%。\n  - **阶段0检查（高杠杆20x）**：盈利0.72% ≥ 0.5%，**触发早期保本**。必须立即将止损调整至入场价86213。\n  - **执行**：由于当前价86836 \u003e 86213，新止损价86213未被触发，继续持仓，但止损位已上移至保本位。\n- **结论**：趋势变化综合评分仅19分，是**短暂波动**。且已触发移动止损阶段0（保本），应将止损调整至86213。**继续持仓**，让利润奔跑。\n\n**仓位控制与可用余额检查（针对潜在新开仓）：**\n- 账户总余额：110.66 USDT。\n- 可用余额：81.33 USDT。\n- 当前市场多周期冲突，无明确A级机会，**不考虑新开仓**。若未来有机会，需确保：\n  1. `position_size_usd` ≥ 20 USDT。\n  2. 实际保证金（`position_size_usd / 杠杆`）≥ 账户总余额的20%（即≥22.13 USDT）。\n  3. **可用余额必须 ≥ 所需保证金（含10%缓冲）**。\n\n**交易逻辑与结论：**\n1.  **持仓管理**：当前BTC多单盈利0.72%，持仓2小时43分钟。趋势变化综合评分仅19分（短暂波动），且已触发移动止损阶段0（高杠杆早期保本）。**应将止损调整至入场价86213**，继续持仓。\n2.  **新开仓**：市场多周期趋势冲突（4小时上升 vs 1小时下跌），无明显转折点或突破信号。BTC虽有极度超卖迹象，但反弹确认信号不足（MACD未金叉、无量）。不符合A级机会标准（信心度\u003c75）。**应观望**。\n3.  **交易频率**：最近1小时交易0次，未达上限，但无合适机会。\n\n**最终决策**：\n1.  调整现有BTC多单的止损至保本位。\n2.  不进行任何新开仓，等待市场多周期趋势重新一致或出现明确的极度超卖反弹确认信号。\n\n---\n\n```json",
  "decision_json": "",
  "account_state": {
    "total_balance": 110.65767354,
    "available_balance": 81.32909921,
    "total_unrealized_profit": -57.342326459999995,
    "position_count": 1,
    "margin_used_pct": 23.541971456816515
  },
  "positions": [
    {
      "symbol": "BTCUSDT",
      "side": "long",
      "position_amt": 0.006,
      "entry_price": 86213.4,
      "mark_price": 86836.65973188,
      "unrealized_profit": 3.73955839,
      "leverage": 20,
      "liquidation_price": 82277.67470884
    }
  ],
  "candidate_coins": [
    "BTCUSDT",
    "SOLUSDT",
    "ETHUSDT",
    "BNBUSDT",
    "XRPUSDT",
    "DOGEUSDT",
    "ADAUSDT",
    "HYPEUSDT"
  ],
  "decisions": null,
  "execution_log": [],
  "success": false,
  "error_message": "获取AI决策失败: 解析AI响应失败: 提取决策失败: 无法找到JSON数组结束"
}